crowdstrike_aidr/__init__.py
crowdstrike_aidr/_client.py
crowdstrike_aidr/_constants.py
crowdstrike_aidr/_exceptions.py
crowdstrike_aidr/_models.py
crowdstrike_aidr/_transform.py
crowdstrike_aidr/_types.py
crowdstrike_aidr/_utils.py
crowdstrike_aidr/models/__init__.py
crowdstrike_aidr/models/ai_guard.py
crowdstrike_aidr/py.typed
crowdstrike_aidr/services/ai_guard.py
crowdstrike_aidr-0.4.2.dist-info/WHEEL
crowdstrike_aidr-0.4.2.dist-info/METADATA
crowdstrike_aidr-0.4.2.dist-info/RECORD
