Metadata-Version: 2.4
Name: crowdstrike-aidr
Version: 0.4.2
Summary: Python SDK for CrowdStrike AIDR.
Author: CrowdStrike
Author-email: CrowdStrike <support@crowdstrike.com>
License-Expression: MIT
Classifier: Typing :: Typed
Classifier: Intended Audience :: Developers
Classifier: Programming Language :: Python :: 3.12
Classifier: Programming Language :: Python :: 3.13
Classifier: Programming Language :: Python :: 3.14
Classifier: Operating System :: OS Independent
Classifier: Operating System :: POSIX
Classifier: Operating System :: MacOS
Classifier: Operating System :: POSIX :: Linux
Classifier: Operating System :: Microsoft :: Windows
Classifier: Topic :: Software Development :: Libraries :: Python Modules
Classifier: License :: OSI Approved :: MIT License
Requires-Dist: httpx~=0.28.1
Requires-Dist: pydantic~=2.12.5
Requires-Dist: typing-extensions~=4.15.0
Requires-Python: >=3.12
